{
  "cli": {
    "version": ">= 16.17.3",
    "appVersionSource": "remote"
  },
  "build": {
    "development": {
      "developmentClient": true,
      "distribution": "internal",
      "ios": {
        "resourceClass": "m-medium"
      }
    },
    "preview": {
      "distribution": "internal",
      "ios": {
        "resourceClass": "m-medium"
      }
    },
    "production": {
      "autoIncrement": true,
      "ios": {
        "resourceClass": "m-medium"
      }
    }
  },
  "submit": {
    "preview": {
      "ios": {
        "appleId": "olamideakomolafe1234@gmail.com",
        "appleTeamId": "X86KTB5ZY7",
        "ascAppId": "6749491841"
      }
    },
    "production": {
      "ios": {
        "appleId": "olamideakomolafe1234@gmail.com",
        "ascAppId": "6749491841",
        "appleTeamId": "X86KTB5ZY7",
        "ascApiKeyPath": "./AuthKey_SweetCue.p8",
        "ascApiKeyId": "YOUR_KEY_ID",
        "ascApiKeyIssuerId": "YOUR_ISSUER_ID"
      }
    }
  }
}
